LICENSE.rst
MANIFEST.in
README.rst
setup.py
wagoner/__init__.py
wagoner/table.py
wagoner/tree.py
wagoner/utils.py
wagoner/word.py
wagoner.egg-info/PKG-INFO
wagoner.egg-info/SOURCES.txt
wagoner.egg-info/dependency_links.txt
wagoner.egg-info/top_level.txt