Metadata-Version: 1.1
Name: wagoner
Version: 1.1
Summary: A random word generator.
Home-page: https://github.com/sbusard/wagoner
Author: Simon Busard
Author-email: simon.busard@gmail.com
License: MIT
Keywords: random word generation
Platform: UNKNOWN
Classifier: Development Status :: 5 - Production/Stable
Classifier: Intended Audience :: Developers
Classifier: Topic :: Utilities
Classifier: License :: OSI Approved :: MIT License
Classifier: Programming Language :: Python :: 2
Classifier: Programming Language :: Python :: 2.7
Classifier: Programming Language :: Python :: 3
Classifier: Programming Language :: Python :: 3.4
